nnconvexity/__init__.py
nnconvexity/euclidean.py
nnconvexity/graph.py
nnconvexity-0.1.1.dist-info/METADATA
nnconvexity-0.1.1.dist-info/WHEEL
nnconvexity-0.1.1.dist-info/licenses/LICENSE.md
nnconvexity-0.1.1.dist-info/RECORD
