Metadata-Version: 2.4
Name: nnconvexity
Version: 0.1.1
Summary: Package for analyzing the convexity of neural networks.
Author-email: Lenka Tetková <lenhy@dtu.dk>, Teresa Dorszewski <tksc@dtu.dk>, Thea Brüsch <theb@dtu.dk>, Tommy Sonne Alstrøm <tsal@dtu.dk>
Maintainer-email: Tommy Sonne Alstrøm <tsal@dtu.dk>, Lenka Tetková <lenhy@dtu.dk>
License-Expression: Apache-2.0
License-File: LICENSE.md
Classifier: Development Status :: 3 - Alpha
Classifier: Intended Audience :: Developers
Classifier: Programming Language :: Python :: 3.9
Classifier: Programming Language :: Python :: 3.10
Classifier: Programming Language :: Python :: 3.11
Classifier: Programming Language :: Python :: 3.12
Classifier: Topic :: Scientific/Engineering :: Artificial Intelligence
Requires-Python: >=3.9
Requires-Dist: joblib
Requires-Dist: numpy
Requires-Dist: pandas
Requires-Dist: python-igraph
Requires-Dist: scipy
Requires-Dist: torch
